alooma/__init__.py
alooma/alooma.py
alooma-0.3.8.dist-info/DESCRIPTION.rst
alooma-0.3.8.dist-info/METADATA
alooma-0.3.8.dist-info/RECORD
alooma-0.3.8.dist-info/WHEEL
alooma-0.3.8.dist-info/metadata.json
alooma-0.3.8.dist-info/top_level.txt
