Metadata-Version: 2.0
Name: alooma
Version: 0.3.8
Summary: Alooma python API
Home-page: UNKNOWN
Author: Yonatan Kiron
Author-email: yonatan@alooma.io
License: UNKNOWN
Keywords: alooma
Platform: UNKNOWN
Requires-Dist: paramiko (>=1.16.0)
Requires-Dist: requests (>=2.9.0)
Requires-Dist: six (>=1.4.1)
Requires-Dist: urllib3 (>=1.13)
